dicewars_pygame/__init__.py
dicewars_pygame/__version__.py
dicewars_pygame/config.py
dicewars_pygame/ctrl_attack.py
dicewars_pygame/ctrl_end.py
dicewars_pygame/ctrl_players.py
dicewars_pygame/ctrl_start.py
dicewars_pygame/ctrl_supply.py
dicewars_pygame/ctrl_view.py
dicewars_pygame/ctrl_window.py
dicewars_pygame/engine.py
dicewars_pygame/events.py
dicewars_pygame/main.py
dicewars_pygame/map_area.py
dicewars_pygame/map_window.py
dicewars_pygame/sounds.py
dicewars_pygame/welcome.py
dicewars_pygame/widgets.py
dicewars_pygame/resources/Anton-Regular.OFL.txt
dicewars_pygame/resources/Anton-Regular.ttf
dicewars_pygame/resources/area.wav
dicewars_pygame/resources/button.wav
dicewars_pygame/resources/defeat.wav
dicewars_pygame/resources/lost.wav
dicewars_pygame/resources/supply.wav
dicewars_pygame/resources/victory.wav
dicewars_pygame/resources/won.wav
dicewars_pygame-0.3.0.dist-info/COPYING
dicewars_pygame-0.3.0.dist-info/METADATA
dicewars_pygame-0.3.0.dist-info/WHEEL
dicewars_pygame-0.3.0.dist-info/entry_points.txt
dicewars_pygame-0.3.0.dist-info/top_level.txt
dicewars_pygame-0.3.0.dist-info/RECORD
