Metadata-Version: 2.1
Name: dicewars-pygame
Version: 0.3.0
Summary: DiceWars game GUI, based on pygame and dicewars
Home-page: https://github.com/scotty007/dicewars_pygame
Author: Thomas Schott
Author-email: scotty@c-base.org
License: UNKNOWN
Platform: UNKNOWN
Classifier: Topic :: Games/Entertainment :: Board Games
Classifier: Intended Audience :: Education
Classifier: Programming Language :: Python :: 3 :: Only
Classifier: Development Status :: 4 - Beta
Classifier: License :: OSI Approved :: GNU General Public License v3 or later (GPLv3+)
Requires-Python: >=3.7
Requires-Dist: dicewars (==0.2.0)
Requires-Dist: pygame (>=2.0.0)
